trefoil/__init__.py
trefoil/analysis/__init__.py
trefoil/analysis/summary.py
trefoil/analysis/tests/__init__.py
trefoil/analysis/tests/test_summary.py
trefoil/analysis/tests/test_timeseries.py
trefoil/analysis/timeseries.py
trefoil/cli/__init__.py
trefoil/cli/calc.py
trefoil/cli/convert.py
trefoil/cli/crs.py
trefoil/cli/extract.py
trefoil/cli/info.py
trefoil/cli/main.py
trefoil/cli/map_eems.py
trefoil/cli/mask.py
trefoil/cli/render_netcdf.py
trefoil/cli/render_tif.py
trefoil/cli/templates/eems_map.html
trefoil/cli/templates/map.html
trefoil/cli/utilities.py
trefoil/cli/warp.py
trefoil/cli/zones.py
trefoil/examples/csv_pivot.py
trefoil/examples/warp_example.py
trefoil/geometry/__init__.py
trefoil/geometry/bbox.py
trefoil/geometry/tests/__init__.py
trefoil/geometry/tests/test_bbox.py
trefoil/netcdf/__init__.py
trefoil/netcdf/conversion.py
trefoil/netcdf/crs.py
trefoil/netcdf/describe.py
trefoil/netcdf/tests/__init__.py
trefoil/netcdf/tests/test_conversion.py
trefoil/netcdf/tests/test_crs.py
trefoil/netcdf/tests/test_variable.py
trefoil/netcdf/utilities.py
trefoil/netcdf/variable.py
trefoil/netcdf/warp.py
trefoil/render/__init__.py
trefoil/render/renderers/__init__.py
trefoil/render/renderers/classified.py
trefoil/render/renderers/legend.py
trefoil/render/renderers/stretched.py
trefoil/render/renderers/tests/__init__.py
trefoil/render/renderers/tests/test_renderers.py
trefoil/render/renderers/unique.py
trefoil/render/renderers/utilities.py
trefoil/test_data/ca_ru_1km.nc
trefoil/test_data/tmin.nc
trefoil/test_data/tmin_zones/tmin_zones.dbf
trefoil/test_data/tmin_zones/tmin_zones.prj
trefoil/test_data/tmin_zones/tmin_zones.shp
trefoil/test_data/tmin_zones/tmin_zones.shx
trefoil/utilities/__init__.py
trefoil/utilities/color.py
trefoil/utilities/conversion.py
trefoil/utilities/format.py
trefoil/utilities/image.py
trefoil/utilities/proj.py
trefoil/utilities/tests/__init__.py
trefoil/utilities/tests/test_color.py
trefoil/utilities/window.py
trefoil-0.4.2.dist-info/METADATA
trefoil-0.4.2.dist-info/WHEEL
trefoil-0.4.2.dist-info/licenses/LICENSE
trefoil-0.4.2.dist-info/RECORD
