Metadata-Version: 2.4
Name: trefoil
Version: 0.4.2
Summary: Geospatial operations with NetCDF files and numpy arrays.
License-File: LICENSE
Author: Conservation Biology Institute
Requires-Python: >=3.9,<3.12
Classifier: Programming Language :: Python :: 3
Classifier: Programming Language :: Python :: 3.9
Classifier: Programming Language :: Python :: 3.10
Classifier: Programming Language :: Python :: 3.11
Requires-Dist: affine (>=1.0)
Requires-Dist: click
Requires-Dist: fiona (>=1.6.0)
Requires-Dist: jinja2
Requires-Dist: netcdf4 (>=1.1.1)
Requires-Dist: numpy
Requires-Dist: palettable
Requires-Dist: pillow (>=9.0.1,<11.0.0)
Requires-Dist: pyproj
Requires-Dist: pytz
Requires-Dist: rasterio (>=1.4.3,<2.0.0)
Requires-Dist: six (>=1.17.0,<2.0.0)
